flask_security/__init__.py
flask_security/babel.py
flask_security/changeable.py
flask_security/cli.py
flask_security/confirmable.py
flask_security/core.py
flask_security/datastore.py
flask_security/decorators.py
flask_security/forms.py
flask_security/recoverable.py
flask_security/registerable.py
flask_security/signals.py
flask_security/utils.py
flask_security/views.py
flask_security/templates/security/_macros.html
flask_security/templates/security/_menu.html
flask_security/templates/security/_messages.html
flask_security/templates/security/change_password.html
flask_security/templates/security/forgot_password.html
flask_security/templates/security/login_user.html
flask_security/templates/security/register_user.html
flask_security/templates/security/reset_password.html
flask_security/templates/security/send_confirmation.html
flask_security/templates/security/email/change_notice.html
flask_security/templates/security/email/change_notice.txt
flask_security/templates/security/email/confirmation_instructions.html
flask_security/templates/security/email/confirmation_instructions.txt
flask_security/templates/security/email/reset_instructions.html
flask_security/templates/security/email/reset_instructions.txt
flask_security/templates/security/email/reset_notice.html
flask_security/templates/security/email/reset_notice.txt
flask_security/templates/security/email/welcome.html
flask_security/templates/security/email/welcome.txt
flask_security/translations/flask_security.pot
flask_security/translations/ar/LC_MESSAGES/flask_security.mo
flask_security/translations/ar/LC_MESSAGES/flask_security.po
flask_security/translations/bg/LC_MESSAGES/flask_security.mo
flask_security/translations/bg/LC_MESSAGES/flask_security.po
flask_security/translations/ca/LC_MESSAGES/flask_security.mo
flask_security/translations/ca/LC_MESSAGES/flask_security.po
flask_security/translations/ca_ES/LC_MESSAGES/flask_security.mo
flask_security/translations/ca_ES/LC_MESSAGES/flask_security.po
flask_security_invenio-3.8.3.dist-info/licenses/AUTHORS
flask_security_invenio-3.8.3.dist-info/licenses/LICENSE
flask_security_invenio-3.8.3.dist-info/METADATA
flask_security_invenio-3.8.3.dist-info/WHEEL
flask_security_invenio-3.8.3.dist-info/top_level.txt
flask_security_invenio-3.8.3.dist-info/RECORD
