Metadata-Version: 2.4
Name: Flask-Security-Invenio
Version: 3.8.3
Summary: "Simple security for Flask apps."
Home-page: https://github.com/inveniosoftware/flask-security-invenio
Author: CERN/TU Wien/JRC
Author-email: info@inveniosoftware.org
License: MIT
Keywords: flask security
Platform: any
Classifier: Development Status :: 5 - Production/Stable
Requires-Python: >=3.6
License-File: LICENSE
License-File: AUTHORS
Requires-Dist: email-validator>=1.0.5
Requires-Dist: speaklater>=1.3
Requires-Dist: Flask-Babel>=2.0.0
Requires-Dist: Flask-Login>=0.4.1
Requires-Dist: Flask-Mail>=0.9.1
Requires-Dist: Flask-Principal>=0.4.0
Requires-Dist: Flask-WTF>=1.1.0
Requires-Dist: Flask>=1.1.4
Requires-Dist: itsdangerous>=2.0
Requires-Dist: markupsafe>=2.1.5
Requires-Dist: passlib>=1.7
Requires-Dist: zxcvbn>=4.4.28
Provides-Extra: tests
Requires-Dist: bcrypt<5.0.0,>=3.1.0; extra == "tests"
Requires-Dist: check-manifest>=0.42; extra == "tests"
Requires-Dist: coverage<6,>=5.3; extra == "tests"
Requires-Dist: Flask-Sphinx-Themes>=1.0.2; extra == "tests"
Requires-Dist: Flask-SQLAlchemy>=2.5.1; extra == "tests"
Requires-Dist: mock>=1.3.0; extra == "tests"
Requires-Dist: msgcheck>=2.9; extra == "tests"
Requires-Dist: pytest-black-ng>=0.4.0; extra == "tests"
Requires-Dist: pytest-cov>=2.10.1; extra == "tests"
Requires-Dist: pytest-flask>=1.0.0; extra == "tests"
Requires-Dist: pytest-isort>=1.2.0; extra == "tests"
Requires-Dist: pytest-pycodestyle>=2.2.0; extra == "tests"
Requires-Dist: pytest-pydocstyle>=2.2.0; extra == "tests"
Requires-Dist: pytest<9,>=6; extra == "tests"
Requires-Dist: sphinx>=4.2.0; extra == "tests"
Dynamic: license-file
